stegy_ui/__init__.py
stegy_ui/__main__.py
stegy_ui/frame_option.py
stegy_ui/stegy_ui.py
stegy_ui/datas/TitleBar.lck
stegy_ui/datas/share32.png
stegy_ui/datas/src.png
stegy_ui/datas/stegy.bmp
stegy_ui/datas/stegy.cnf
stegy_ui/datas/stegy.ico
stegy_ui/tkinterdnd2/TkinterDnD.py
stegy_ui/tkinterdnd2/__init__.py
stegy_ui/ui/title.py
pystegy_ui-0.0.2.dist-info/LICENSE
pystegy_ui-0.0.2.dist-info/METADATA
pystegy_ui-0.0.2.dist-info/WHEEL
pystegy_ui-0.0.2.dist-info/top_level.txt
pystegy_ui-0.0.2.dist-info/RECORD
